yinstabot/__init__.py
yinstabot/custom.py
yinstabot/utils.py
yinstabot/workspace.py
yinstabot/api/__init__.py
yinstabot/api/api.py
yinstabot/api/api_login.py
yinstabot/api/api_photo.py
yinstabot/api/api_story.py
yinstabot/api/api_video.py
yinstabot/api/config.py
yinstabot/api/devices.py
yinstabot/api/prepare.py
yinstabot/bot/__init__.py
yinstabot/bot/bot.py
yinstabot/bot/bot_archive.py
yinstabot/bot/bot_block.py
yinstabot/bot/bot_checkpoint.py
yinstabot/bot/bot_comment.py
yinstabot/bot/bot_delete.py
yinstabot/bot/bot_direct.py
yinstabot/bot/bot_filter.py
yinstabot/bot/bot_follow.py
yinstabot/bot/bot_get.py
yinstabot/bot/bot_like.py
yinstabot/bot/bot_photo.py
yinstabot/bot/bot_stats.py
yinstabot/bot/bot_story.py
yinstabot/bot/bot_support.py
yinstabot/bot/bot_unfollow.py
yinstabot/bot/bot_unlike.py
yinstabot/bot/bot_video.py
yinstabot-2.5.3.dist-info/LICENSE
yinstabot-2.5.3.dist-info/METADATA
yinstabot-2.5.3.dist-info/WHEEL
yinstabot-2.5.3.dist-info/entry_points.txt
yinstabot-2.5.3.dist-info/top_level.txt
yinstabot-2.5.3.dist-info/RECORD
