Metadata-Version: 2.1
Name: yinstabot
Version: 2.5.3
Summary: Instagram bot
Home-page: https://github.com/yedhrab/YInstabot
Author: Yunus Emre Ak
Author-email: yedhrab@gmail.com
License: MIT
Download-URL: https://github.com/yedhrab/YInstaBot/releases/download/2.5.3/yinstabot-2.5.3.tar.gz
Keywords: instabot,yinstabot,instagrambot,neoinstabot,instabot-py
Platform: UNKNOWN
Classifier: Development Status :: 3 - Alpha
Classifier: Intended Audience :: Developers
Classifier: Topic :: Software Development :: Build Tools
Classifier: License :: OSI Approved :: MIT License
Classifier: Programming Language :: Python :: 3
Classifier: Programming Language :: Python :: 3.4
Classifier: Programming Language :: Python :: 3.5
Classifier: Programming Language :: Python :: 3.6
Requires-Dist: ypackage
Requires-Dist: certifi
Requires-Dist: chardet
Requires-Dist: huepy
Requires-Dist: idna
Requires-Dist: lazy
Requires-Dist: post
Requires-Dist: public
Requires-Dist: pytz
Requires-Dist: query
Requires-Dist: requests
Requires-Dist: six
Requires-Dist: tqdm
Requires-Dist: urllib3
Requires-Dist: wrapt
